PgsFile
