Metadata-Version: 2.4
Name: PgsFile
Version: 0.6.6
Summary: This module streamlines Python package management, script execution, file handling, web scraping, and multimedia downloads. It supports LLM-based NLP tasks like OCR, tokenization, lemmatization, idiom extraction, POS tagging, NER, ATE, dependency parsing, MDD, WSD, LIWC, MIP analysis, text classification, and Chinese-English sentence alignment. Additionally, it generates word lists and data visualizations, making it a practical tool for data scraping and analysis—ideal for literary stud
Home-page: https://github.com/Petercusin/PgsFile
Author: Dr. Guisheng Pan is an instructor at Shanghai University of Finance and Economics (SUFE).
Author-email: panguisheng@sufe.edu.cn
License: Educational free
Classifier: Programming Language :: Python :: 3
Classifier: License :: Free For Educational Use
Classifier: Operating System :: OS Independent
Requires-Python: >=3.8
License-File: LICENSE
Requires-Dist: pandas
Requires-Dist: python-docx
Requires-Dist: pip
Requires-Dist: requests
Requires-Dist: fake-useragent
Requires-Dist: lxml
Requires-Dist: pimht
Requires-Dist: pysbd
Requires-Dist: nlpir-python
Requires-Dist: pillow
Requires-Dist: liwc
Dynamic: author
Dynamic: author-email
Dynamic: classifier
Dynamic: description
Dynamic: description-content-type
Dynamic: home-page
Dynamic: license
Dynamic: license-file
Dynamic: requires-dist
Dynamic: requires-python
Dynamic: summary
